cafex_core/__init__.py
cafex_core/cafex_cli.py
cafex_core/handlers/__init__.py
cafex_core/handlers/file_handler.py
cafex_core/handlers/folder_handler.py
cafex_core/logging/__init__.py
cafex_core/logging/colargulog.py
cafex_core/logging/logger_.py
cafex_core/parsers/__init__.py
cafex_core/parsers/html_parser.py
cafex_core/parsers/json_parser.py
cafex_core/parsers/xml_parser.py
cafex_core/reporting_/__init__.py
cafex_core/reporting_/report_generator.py
cafex_core/reporting_/reporting.py
cafex_core/reporting_/screenshot_utils.py
cafex_core/reporting_/step_decorator.py
cafex_core/reporting_/_report_viewer/__init__.py
cafex_core/reporting_/_report_viewer/app.js
cafex_core/reporting_/_report_viewer/index.html
cafex_core/reporting_/_report_viewer/styles.css
cafex_core/reporting_/_report_viewer/_server_scripts/__init__.py
cafex_core/reporting_/_report_viewer/_server_scripts/_server_generator.py
cafex_core/reporting_/_report_viewer/_server_scripts/_server_launcher.py
cafex_core/singletons_/__init__.py
cafex_core/singletons_/request_.py
cafex_core/singletons_/session_.py
cafex_core/utils/__init__.py
cafex_core/utils/assertions.py
cafex_core/utils/config_utils.py
cafex_core/utils/core_security.py
cafex_core/utils/custom_encryption.py
cafex_core/utils/date_time_utils.py
cafex_core/utils/elastic_search_utils.py
cafex_core/utils/exceptions.py
cafex_core/utils/file_reader_utils.py
cafex_core/utils/file_transfer_utils.py
cafex_core/utils/item_attribute_accessor.py
cafex_core/utils/regex_constants.py
cafex_core/utils/ssh_handler.py
cafex_core/utils/apache_utils/__init__.py
cafex_core/utils/apache_utils/apache_air_flow_utils.py
cafex_core/utils/apache_utils/nifi_process_group_utils.py
cafex_core/utils/apache_utils/nifi_processor_utils.py
cafex_core/utils/hooks_/__init__.py
cafex_core/utils/hooks_/hook_helper.py
cafex_core/utils/hooks_/hook_util.py
cafex_core/utils/hooks_/pytest_add_option_hook.py
cafex_core/utils/hooks_/pytest_after_scenario_hook.py
cafex_core-1.0.0.dist-info/METADATA
cafex_core-1.0.0.dist-info/WHEEL
cafex_core-1.0.0.dist-info/entry_points.txt
cafex_core-1.0.0.dist-info/top_level.txt
cafex_core-1.0.0.dist-info/RECORD
