Metadata-Version: 2.4
Name: cafex-core
Version: 1.0.0
Summary: Core Package
Author-email: QA Automation Team <qa_automation@gmail.com>
Project-URL: Homepage, https://example.com
Project-URL: Documentation, https://readthedocs.org
Project-URL: Repository, https://github.com/me/spam.git
Project-URL: Issues, https://github.com/me/spam/issues
Project-URL: Changelog, https://github.com/me/spam/blob/master/CHANGELOG.md
Classifier: Programming Language :: Python :: 3
Classifier: Operating System :: OS Independent
Requires-Python: >=3.12
Requires-Dist: pytest-bdd==7.3.0
Requires-Dist: pytest==8.3.3
Requires-Dist: pytest-xdist==3.6.1
Requires-Dist: lxml==4.9.3
Requires-Dist: pandas==2.2.1
Requires-Dist: nipyapi==0.19.1
Requires-Dist: PyYAML==6.0.1
Requires-Dist: pycryptodome==3.20.0
Requires-Dist: python-json-logger==2.0.7
Requires-Dist: py7zr==0.21.0
Requires-Dist: beautifulsoup4==4.12.3
Requires-Dist: xlrd==2.0.1
Requires-Dist: paramiko==3.4.0
Requires-Dist: boto3==1.34.57
Requires-Dist: scikit-image==0.22.0
Requires-Dist: Pillow==10.2.0
Requires-Dist: Nested-lookup==0.2.25
Requires-Dist: objectpath==0.6.1
Requires-Dist: json2xml==4.1.0
Requires-Dist: lockfile==0.12.2
Requires-Dist: PyAutoGUI==0.9.54; platform_system == "Windows"
Requires-Dist: allure-pytest==2.13.2
Requires-Dist: requests==2.31.0
Requires-Dist: pypsexec==0.3.0
Requires-Dist: pymsteams==0.2.2
Requires-Dist: requests-kerberos==0.14.0
Requires-Dist: requests_ntlm==1.2.0
Requires-Dist: dicttoxml==1.7.16
Requires-Dist: python-dotenv==1.0.1
Requires-Dist: openpyxl==3.1.5
Requires-Dist: python-docx==1.1.2
Requires-Dist: pyMuPDF==1.23.26
Provides-Extra: ui
Requires-Dist: cafex-ui>=1.0.0; extra == "ui"
Provides-Extra: db
Requires-Dist: cafex-db>=1.0.0; extra == "db"
Provides-Extra: api
Requires-Dist: cafex-api>=1.0.0; extra == "api"
Provides-Extra: all
Requires-Dist: cafex-ui>=1.0.0; extra == "all"
Requires-Dist: cafex-api>=1.0.0; extra == "all"
Requires-Dist: cafex-db>=1.0.0; extra == "all"
